MANIFEST.in
README.rst
requirements.txt
setup.cfg
setup.py
djmicrosip_organizador/__init__.py
djmicrosip_organizador/__init__.pyc
djmicrosip_organizador/autocomplete_light_registry.pyc
djmicrosip_organizador/config.pyc
djmicrosip_organizador/forms.pyc
djmicrosip_organizador/models.pyc
djmicrosip_organizador/urls.pyc
djmicrosip_organizador/views.pyc
djmicrosip_organizador.egg-info/PKG-INFO
djmicrosip_organizador.egg-info/SOURCES.txt
djmicrosip_organizador.egg-info/dependency_links.txt
djmicrosip_organizador.egg-info/requires.txt
djmicrosip_organizador.egg-info/top_level.txt
djmicrosip_organizador/custom_db/__init__.py
djmicrosip_organizador/custom_db/__init__.pyc
djmicrosip_organizador/custom_db/procedures.pyc
djmicrosip_organizador/static/djmicrosip_organizador/css/32px.png
djmicrosip_organizador/static/djmicrosip_organizador/css/40px.png
djmicrosip_organizador/static/djmicrosip_organizador/css/style.css
djmicrosip_organizador/static/djmicrosip_organizador/css/style.min.css
djmicrosip_organizador/static/djmicrosip_organizador/css/throbber.gif
djmicrosip_organizador/static/djmicrosip_organizador/js/core.js
djmicrosip_organizador/static/djmicrosip_organizador/js/intro.js
djmicrosip_organizador/static/djmicrosip_organizador/js/make_tree.js
djmicrosip_organizador/static/djmicrosip_organizador/js/manage_tags.js
djmicrosip_organizador/static/djmicrosip_organizador/js/manage_tree.js
djmicrosip_organizador/static/djmicrosip_organizador/js/misc.js
djmicrosip_organizador/static/djmicrosip_organizador/js/outro.js
djmicrosip_organizador/static/djmicrosip_organizador/js/sample.js
djmicrosip_organizador/static/djmicrosip_organizador/js/vakata-jstree.js
djmicrosip_organizador/static/djmicrosip_organizador/js/jstree/jstree.checkbox.js
djmicrosip_organizador/static/djmicrosip_organizador/js/jstree/jstree.contextmenu.js
djmicrosip_organizador/static/djmicrosip_organizador/js/jstree/jstree.dnd.js
djmicrosip_organizador/static/djmicrosip_organizador/js/jstree/jstree.js
djmicrosip_organizador/static/djmicrosip_organizador/js/jstree/jstree.search.js
djmicrosip_organizador/static/djmicrosip_organizador/js/jstree/jstree.sort.js
djmicrosip_organizador/static/djmicrosip_organizador/js/jstree/jstree.state.js
